notification_sound_windows/__init__.py
notification_sound_windows/__main__.py
notification_sound_windows/audio_player.py
notification_sound_windows/config.py
notification_sound_windows/server.py
notification_sound_windows-0.1.0.dist-info/METADATA
notification_sound_windows-0.1.0.dist-info/WHEEL
notification_sound_windows-0.1.0.dist-info/entry_points.txt
notification_sound_windows-0.1.0.dist-info/licenses/LICENSE
notification_sound_windows-0.1.0.dist-info/RECORD
