Metadata-Version: 2.4
Name: notification-sound-windows
Version: 0.1.0
Summary: Windows notification sound player for MCP servers
Project-URL: Homepage, https://github.com/your-username/notification-sound-windows
Project-URL: Repository, https://github.com/your-username/notification-sound-windows
Project-URL: Issues, https://github.com/your-username/notification-sound-windows/issues
Project-URL: Documentation, https://github.com/your-username/notification-sound-windows/blob/main/README.md
Author-email: Package Author <author@example.com>
License-Expression: MIT
License-File: LICENSE
Keywords: audio,mcp,notification,sound,windows
Classifier: Development Status :: 4 - Beta
Classifier: Intended Audience :: Developers
Classifier: License :: OSI Approved :: MIT License
Classifier: Operating System :: Microsoft :: Windows
Classifier: Programming Language :: Python :: 3
Classifier: Programming Language :: Python :: 3.10
Classifier: Programming Language :: Python :: 3.11
Classifier: Programming Language :: Python :: 3.12
Classifier: Topic :: Communications
Classifier: Topic :: Multimedia :: Sound/Audio :: Players
Classifier: Topic :: Software Development :: Libraries :: Python Modules
Requires-Python: >=3.10
Requires-Dist: fastmcp>=0.1.0
Requires-Dist: mcp>=1.2.0
Requires-Dist: pydub>=0.25.1
Requires-Dist: pywin32>=306; sys_platform == 'win32'
Provides-Extra: dev
Requires-Dist: black>=23.0.0; extra == 'dev'
Requires-Dist: mypy>=1.0.0; extra == 'dev'
Requires-Dist: pre-commit>=3.0.0; extra == 'dev'
Requires-Dist: pytest-asyncio>=0.21.0; extra == 'dev'
Requires-Dist: pytest-cov>=4.0.0; extra == 'dev'
Requires-Dist: pytest>=7.0.0; extra == 'dev'
Requires-Dist: ruff>=0.1.0; extra == 'dev'
Provides-Extra: test
Requires-Dist: pytest-asyncio>=0.21.0; extra == 'test'
Requires-Dist: pytest-cov>=4.0.0; extra == 'test'
Requires-Dist: pytest-mock>=3.10.0; extra == 'test'
Requires-Dist: pytest>=7.0.0; extra == 'test'
